<?xml version="1.0" encoding="utf-8" standalone="no"?><business id="FPKJ">
    <body>
        <input>
            <fpqqlsh>89920190619155105</fpqqlsh>
            <jsbh>110101201707010057~~499000152456</jsbh>
            <fplxdm>025</fplxdm>
            <kplx>1</kplx>
            <yhlx>0</yhlx>
            <ghdwsbh>91320191MA1ML4CL25</ghdwsbh>
            <ghdwmc>南京数族信息科技有限公司</ghdwmc>
            <fyxm count="1">
                <group xh="1">
                    <fphxz>0</fphxz>
                    <spmc>兰博基尼跑车</spmc>
                    <spsl/>
                    <hsdj/>
                    <hsje>-1356000</hsje>
                    <sl>0.13</sl>
                    <se>-156000</se>
                    <spbm>1090305010800000000</spbm>
                    <zxbm/>
                    <yhzcbs>0</yhzcbs>
                    <lslbs/>
                    <zzstsgl/>
                </group>
            </fyxm>
            <bz>备注</bz>
            <skr>收款人</skr>
            <kpr>开票人</kpr>
            <yfpdm/>
            <yfphm/>
            <sprsjh>zhaokun@shuzutech.com</sprsjh>
        </input>
    </body>
</business>