<?xml version="1.0" encoding="utf-8"?>
<business id="KHXXTS">
    <body>
        <input>
            <channelId>603</channelId>
            <clientName>安徽测试账户8</clientName>
            <provinceno>340000</provinceno>
            <cityno></cityno>
            <dispatch>1</dispatch>
            <nsrsbh>154413222300055</nsrsbh>
            <businessAddress>安徽测试商户地址8</businessAddress>
            <tel>16629135036</tel>
            <openBank>招商银行7</openBank>
            <accountNo>6226090212478759</accountNo>
            <phone>16829135036</phone>
            <contact>admin</contact>
            <idno>342224199203080876</idno>
            <salerMobile></salerMobile>
            <sbbh></sbbh>
            <hxbbh></hxbbh>
            <xmmc></xmmc>
            <defautGoods>代收民航发展基金</defautGoods>
            <goodsId>6130000000000000000</goodsId>
            <taxRate>0.06</taxRate>
            <kpr></kpr>
        </input>
    </body>
</business>
